pydockingorg/__init__.py
pydockingorg/dockingorg.py
pyDockingOrg-1.0.4.dist-info/LICENSE
pyDockingOrg-1.0.4.dist-info/METADATA
pyDockingOrg-1.0.4.dist-info/WHEEL
pyDockingOrg-1.0.4.dist-info/top_level.txt
pyDockingOrg-1.0.4.dist-info/RECORD
