Metadata-Version: 2.1
Name: pyDockingOrg
Version: 1.0.4
Summary: A python interface to query sw.docking.org for Enamine structures based on Matteo Ferla work. This is the old interface that uses two interations (hit lists) to get results. 
Author-email: Mateusz bieniek <bieniekmat@gmail.com>
License: Apache License
Project-URL: Homepage, https://github.com/bieniekmateusz/pyDockingOrg
Keywords: Enamine database
Classifier: Programming Language :: Python
Classifier: Programming Language :: Python :: 3
Requires-Python: >=3.9
License-File: LICENSE
Requires-Dist: pandas
Requires-Dist: requests
